thart_automata-0.2.0.dist-info/licenses/LICENSE
thart_core/__init__.py
thart_core/automata.py
thart_core/preprocessors.py
thart_automata-0.2.0.dist-info/METADATA
thart_automata-0.2.0.dist-info/WHEEL
thart_automata-0.2.0.dist-info/entry_points.txt
thart_automata-0.2.0.dist-info/top_level.txt
thart_automata-0.2.0.dist-info/RECORD
