Metadata-Version: 2.4
Name: thart-automata
Version: 0.2.0
Summary: A Python package for THART-n automata.
Home-page: https://github.com/Mohammed-farhaan-math/THARTn
Author: ORG: Mohammed Farhaan
License-File: LICENSE
Requires-Dist: numpy
Dynamic: author
Dynamic: home-page
Dynamic: license-file
Dynamic: requires-dist
Dynamic: summary
